[
  {"rule_id":"BT001","scenario":"跨越小型河川(障碍宽度<10m)","obstacle_width_range":"<10m","bridge_type":"应急轻便桥(拼装式)","capacity_desc":"单车道宽4.2m,可承载荷不超过40吨,轮式轴压13t","setup_time":"6人作业,40分钟内完成","notes":"临时应急抢通,人力拼装,劳动强度较高"},
  {"rule_id":"BT002","scenario":"跨越小型河川(障碍宽度<10m)","obstacle_width_range":"<10m","bridge_type":"机械化桥(小跨度)","capacity_desc":"单车道宽2.6m,可承载荷不超过30吨","setup_time":"2人作业,10分钟内完成","notes":"纯机械化作业,劳动强度低,自行驶到现场"},
  {"rule_id":"BT003","scenario":"跨越小型河川(障碍宽度10-15m)","obstacle_width_range":"10-15m","bridge_type":"机械化桥(应急重型)","capacity_desc":"单车道宽3.2m,可承载荷不超过60吨","setup_time":"3人作业,15分钟完成","notes":"机械化作业,自行驶到现场,适应河川深度不大于5m"},
  {"rule_id":"BT004","scenario":"跨越中型河川(障碍宽度15-30m)","obstacle_width_range":"15-30m","bridge_type":"机械化桥(带桥脚)","capacity_desc":"单车道宽3.8m,可承载荷不超过60吨","setup_time":"7人作业,20分钟/跨","notes":"自带桥脚,适应河川深度不大于5m,水流速不超2m/s"},
  {"rule_id":"BT005","scenario":"跨越中型河川(障碍宽度15-30m)","obstacle_width_range":"15-30m","bridge_type":"装配式钢桥(321/ZB200/CB系列)","capacity_desc":"单车道宽3.7m,双车道4.2m,可承载汽-20级","setup_time":"12-20人作业,约4.5-15小时","notes":"人力拼装,劳动强度高,需借助车辆运输到现场"},
  {"rule_id":"BT006","scenario":"跨越大型河川(障碍宽度30-50m)","obstacle_width_range":"30-50m","bridge_type":"机械化桥(应急大跨度)","capacity_desc":"单车道宽4m,可承载荷不超过60吨","setup_time":"6人作业,1.5-2小时","notes":"多辆车自行驶到现场,需要较宽阔场地"},
  {"rule_id":"BT007","scenario":"跨越大型河川(障碍宽度50-200m)","obstacle_width_range":"50-200m","bridge_type":"动力舟桥(连成整桥)","capacity_desc":"单车道宽5m,可承载荷不超过60吨","setup_time":"30-100人配合,1-2小时","notes":"大量舟桥车辆自行驶到现场,水流速不大于3m/s"},
  {"rule_id":"BT008","scenario":"陡岸峡谷(水流急不易架墩)","obstacle_width_range":"不限","bridge_type":"索道桥或溜索","capacity_desc":"小型设备物资运输","setup_time":"视情况","notes":"为开辟生命通道,解决小型设备物质运输"}
]
